{
  "site": {
    "title": "CL游戏姬",
    "subtitle": "小黄油,galgame,cos福利… 免费下载！",
    "footer": "解压密码: 初恋的奇妙屋"
  },
  "posts": [
    {
      "id": 5,
      "title": "更新[国风仙侠RPG/像素动态] 合欢宗女修传 Ver0.25 官方中文版 [640M]",
      "description": "作者：#蓝月虫 标签：#精品 #RPG #官中 #PC #安卓joi #像素,无码,国风,仙侠,动态  游戏简介： 这是一个黑莲花的重生复仇修仙游戏。 作为女主",
      "content": "<p>作者：#蓝月虫</p>\n<p>标签：#精品 #RPG #官中 #PC #安卓joi #像素,无码,国风,仙侠,动态</p>\n<p><a href=\"https://imagetwist.com/66sdy430cyxk/105edece27d92a2064d348b84fedf8f1.jpg.html\"><img src=\"https://img166.imagetwist.com/th/63286/66sdy430cyxk.jpg\" alt=\"\"></a></p>\n<p>游戏简介：<br>这是一个黑莲花的重生复仇修仙游戏。<br>作为女主的玩家，不仅要逃离家庭，还有修仙路上的人心叵测。<br>一路向前，成就一代大帝。<br><img src=\"https://image.acg.lol/file/2025/09/16/4-3.png\" alt=\"\"><br>更新内容：<br>v0.175<br>主要是修改了BUG：<br>1、隐藏地图不能看<br>2、白天休息到不了晚上<br>3、打坐时间没变化<br>4、休息后立绘重叠<br>5、增加了牧渺渺、二长老、二师兄行走图</p>\n<p>更新内容：<br>v0.251更新<br>1、修改了部分BUG<br>2、砍掉了要刷师兄、师傅和师姐好感<br>3、砍掉日，只剩月份<br>4、做出大地图，后续逐渐开启<br>5、宗门大比做完了<br>6、增加三套衣服（战斗里也有）<br>7、醉仙居剧情开启<br>8、救出亲妈已经做完<br><img src=\"https://image.acg.lol/file/2025/09/16/4-4.png\" alt=\"\"><br>更新内容<br>1、部分行走图增加修改<br>2、给的装备可以穿了<br>3、序章杀了15人后，可以杀丫鬟了，杀够25人，可以杀马夫。<br>4、云嬷嬷剧情已增加<br>5、打坐CG已经重置<br>6、突破境界增加了过程动态<br>7、睡觉CG增加<br>8、被马夫追上啪啪啪会出BUG已修改</p>\n<p><img src=\"https://image.acg.lol/file/2025/09/16/4-5.png\" alt=\"\"></p>\n<p>满月密码：0815<br>国庆密码：1001</p>\n<p>百度网盘：B663777<br>链接: <a href=\"https://pan.baidu.com/s/1VrwBSZZJqESzqCvhv_9iYg?pwd=2h6b\">https://pan.baidu.com/s/1VrwBSZZJqESzqCvhv_9iYg?pwd=2h6b</a> 提取码: 2h6b<br>———————————–</p>\n<p>UC网盘：B663777<br><a href=\"https://drive.uc.cn/s/5d8e1927293b4\">https://drive.uc.cn/s/5d8e1927293b4</a>密码：Mcmg</p>\n",
      "contentMd": "作者：#蓝月虫\n\n标签：#精品 #RPG #官中 #PC #安卓joi #像素,无码,国风,仙侠,动态\n\n[![](https://img166.imagetwist.com/th/63286/66sdy430cyxk.jpg)](https://imagetwist.com/66sdy430cyxk/105edece27d92a2064d348b84fedf8f1.jpg.html)\n\n游戏简介：  \n这是一个黑莲花的重生复仇修仙游戏。  \n作为女主的玩家，不仅要逃离家庭，还有修仙路上的人心叵测。  \n一路向前，成就一代大帝。  \n![](https://image.acg.lol/file/2025/09/16/4-3.png)  \n更新内容：  \nv0.175  \n主要是修改了BUG：  \n1、隐藏地图不能看  \n2、白天休息到不了晚上  \n3、打坐时间没变化  \n4、休息后立绘重叠  \n5、增加了牧渺渺、二长老、二师兄行走图\n\n更新内容：  \nv0.251更新  \n1、修改了部分BUG  \n2、砍掉了要刷师兄、师傅和师姐好感  \n3、砍掉日，只剩月份  \n4、做出大地图，后续逐渐开启  \n5、宗门大比做完了  \n6、增加三套衣服（战斗里也有）  \n7、醉仙居剧情开启  \n8、救出亲妈已经做完  \n![](https://image.acg.lol/file/2025/09/16/4-4.png)  \n更新内容  \n1、部分行走图增加修改  \n2、给的装备可以穿了  \n3、序章杀了15人后，可以杀丫鬟了，杀够25人，可以杀马夫。  \n4、云嬷嬷剧情已增加  \n5、打坐CG已经重置  \n6、突破境界增加了过程动态  \n7、睡觉CG增加  \n8、被马夫追上啪啪啪会出BUG已修改\n\n![](https://image.acg.lol/file/2025/09/16/4-5.png)\n\n满月密码：0815  \n国庆密码：1001\n\n百度网盘：B663777  \n链接: [https://pan.baidu.com/s/1VrwBSZZJqESzqCvhv\\_9iYg?pwd=2h6b](https://pan.baidu.com/s/1VrwBSZZJqESzqCvhv_9iYg?pwd=2h6b) 提取码: 2h6b  \n———————————–\n\nUC网盘：B663777  \n[https://drive.uc.cn/s/5d8e1927293b4](https://drive.uc.cn/s/5d8e1927293b4)密码：Mcmg",
      "image": "",
      "link": "/article.html?id=5",
      "download": "https://pan.baidu.com/s/1VrwBSZZJqESzqCvhv_9iYg?pwd=2h6b\">https://pan.baidu.com/s/1VrwBSZZJqESzqCvhv_9iYg?pwd=2h6b</a",
      "category": "PC",
      "gradient": "linear-gradient(135deg,#2ECC71,#27AE60)",
      "icon": "fa-gamepad",
      "author": "CL",
      "authorAvatar": "恋",
      "views": "0",
      "comments": 2,
      "date": "2026年5年25日"
    },
    {
      "id": 4,
      "title": "更新[亚洲风SLG/堕母/动态] 妈妈为何这样 他让她堕落 He Maid Her Fall v0.8.6  官中步兵版+自带全回想 [PC+安卓8.60G]",
      "description": "游戏简介： 《He Maid Her Fall》是一部母子关系的 NTR，充满了真挚而又令人心碎的时刻。 讲述母子二人的生活被自私的外人颠覆，他们努力维持关系不",
      "content": "<p><img decoding=\"async\" src=\"https://image.acg.lol/file/2025/06/28/photo_5_2025-06-27_18-16-59.jpg\" class=\"lazy\"></p>\n<p>游戏简介：<br>\n《He Maid Her Fall》是一部母子关系的 NTR，充满了真挚而又令人心碎的时刻。<br>\n讲述母子二人的生活被自私的外人颠覆，他们努力维持关系不破裂的故事。<br>\n正当约翰尼认为他的大学生活不会变得更糟时，<br>\n约翰尼的母亲凯特被提供了一份女佣的工作来补偿他所遭受的痛苦。<br>\n唯一的转折是……她的工作是照顾伤害她儿子的人；他的欺凌者。</p>\n<p><img decoding=\"async\" src=\"https://image.acg.lol/file/2025/06/28/photo_1_2025-06-27_18-16-59.jpg\" class=\"lazy\"></p>\n<p>强尼的大学生活并不顺心。<br>\n为了改善儿子的处境、支持他追逐梦想，他的妈妈凯特找到了一份女仆的工作。<br>\n然而……她的雇主偏偏是那个专门找强尼麻烦的家伙：他的霸凌者。</p>\n<p><img decoding=\"async\" src=\"https://image.acg.lol/file/2025/06/28/photo_9_2025-06-27_18-16-59.jpg\" class=\"lazy\"></p>\n<p>现有特色<br>\n多线叙事<br>\nCG特效动画<br>\n动画精灵<br>\n精彩预告<br>\n20万字扣人心弦、搔到痒处的精彩故事<br>\n20+ 性爱场景<br>\n50+ 特效场景</p>\n<p><img decoding=\"async\" src=\"https://image.acg.lol/file/2025/06/28/photo_10_2025-06-27_18-16-59.jpg\" class=\"lazy\"></p>\n<p>更新日志：<br>\nv0.8.6<br>\n・新增 15000 个新词（总计：231500 个）<br>\n・新增 6 组剧情内容（总计：69 组）<br>\n・新增 3 段暧昧场景剧情（总计：27 段）</p>\n<p><img decoding=\"async\" src=\"https://image.acg.lol/file/2025/06/28/photo_7_2025-06-27_18-16-59.jpg\" class=\"lazy\"></p>\n<p>百度网盘：B919111<br>\n链接: <a href=\"https://pan.baidu.com/s/1imCcKXTb4vqR2S13MYfcTw?pwd=86xn\">https://pan.baidu.com/s/1imCcKXTb4vqR2S13MYfcTw?pwd=86xn</a> 提取码: 86xn<br>\n————————————</p>\n<p>UC网盘：B919111<br>\n<a href=\"https://drive.uc.cn/s/a6df77191c214\">https://drive.uc.cn/s/a6df77191c214</a>密码：CxfV</p>",
      "image": "",
      "link": "/article.html?id=4",
      "download": "https://pan.baidu.com/s/1imCcKXTb4vqR2S13MYfcTw?pwd=86xn\">https://pan.baidu.com/s/1imCcKXTb4vqR2S13MYfcTw?pwd=86xn</a",
      "category": "AZ",
      "gradient": "linear-gradient(135deg,#3498DB,#2980B9)",
      "icon": "fa-gamepad",
      "author": "CL",
      "authorAvatar": "恋",
      "views": "0",
      "comments": 0,
      "date": "2026年5年25日"
    },
    {
      "id": 3,
      "title": "大更新[沙盒SLG/家园后宫/全动态] 幸福岛幻想 V1.2.0.0 官中步兵版+DLC+存档 [8.30G]",
      "description": "开发者：#HappyCreator 贩卖日：2025 年 7 月 12 日 标签：#SLG #官中 #PC #动态,无码,后宫,巨乳,爆乳,自由,探索,家园,生",
      "content": "<div align=\"left\">\n<div align=\"left\"><span style=\"font-family: keai;\">开发者：#HappyCreator</span></div>\n<div align=\"left\"><span style=\"font-family: keai;\">贩卖日：2025 年 7 月 12 日</span></div>\n<div align=\"left\"><span style=\"font-family: keai;\">标签：#SLG #官中 #PC #动态,无码,后宫,巨</span><span style=\"font-family: keai;\">乳,爆乳,自由,探索,家园,生活</span></div>\n<div align=\"left\"><img decoding=\"async\" src=\"https://img34.imagetwist.com/th/70270/mn6sf5n4c1q4.jpg\" ></div>\n</div>\n<p>游戏剧情<br>\n冒险家“罗恩”带领一只探险小队，调查常年风暴肆虐的漩涡中心，结果探险船在风暴中解体。<br>\n昏迷中被海水冲刷到了一个几乎与世隔绝的小岛。<br>\n醒来后，村长告诉他这里是“幸福岛”，想要离开就要等待下一次“祭祀日”，于是罗恩就住了下来。<br>\n在这里他结识了几位美丽的女孩，村长的女儿、妩媚的未亡人、神秘的女神、新婚的少妇等等。<br>\n在这些红颜知己的帮助下，成功解开了岛上风暴的秘密，并发现了远古的宝藏。<br>\n<img decoding=\"async\" src=\"https://img34.imagetwist.com/th/70270/0hdxswtal8uj.jpg\" ><br>\n游戏元素<br>\n【1】全岛自由移动，跟随玩家的操作肆意闲逛；<br>\n【2】钓鱼、拾荒等日常玩法；<br>\n【3】每个故事流程中都穿插小游戏，给玩家解闷；<br>\n【4】丰富的动态CG动画，每个细节动感十足；</p>\n<p><img decoding=\"async\" src=\"https://img34.imagetwist.com/th/70270/ctzxbb5sa692.jpg\" ></p>\n<p><img decoding=\"async\" src=\"https://img34.imagetwist.com/th/70270/zwwjvhvjbo77.jpg\" ></p>\n<p>更新日志：<br>\n发布2026年05月21日<br>\nv1.2.0.0<br>\n《幸福岛幻想》[“性”福生活]正式上线！全新角色＋剧情大更新<br>\n新 DLC「性福人生」新增两位全新角色，并扩充岛上尚未接触过的女性的亲密故事。<br>\n同时还增加了一些扭蛋手办收集、战斗等全新玩法。<br>\n准备迎接更火热、更甜蜜的互动，达到极致性福！</p>\n<p><img decoding=\"async\" src=\"https://img34.imagetwist.com/th/70270/kz9eynr2v816.jpg\" ></p>\n<p>百度网盘：B920888<br>\n链接: <a href=\"https://pan.baidu.com/s/1MwvniD-Ao0SHjlQ9-z1DTg?pwd=je24\">https://pan.baidu.com/s/1MwvniD-Ao0SHjlQ9-z1DTg?pwd=je24</a> 提取码: je24<br>\n———————————–</p>\n<p>UC网盘：B920888<br>\n<a href=\"https://drive.uc.cn/s/8824f7bd64344\">https://drive.uc.cn/s/8824f7bd64344</a>密码：UQqg</p>",
      "image": "https://img34.imagetwist.com/th/70270/mn6sf5n4c1q4.jpg",
      "link": "/article.html?id=3",
      "download": "https://pan.baidu.com/s/1MwvniD-Ao0SHjlQ9-z1DTg?pwd=je24\">https://pan.baidu.com/s/1MwvniD-Ao0SHjlQ9-z1DTg?pwd=je24</a",
      "category": "PC",
      "gradient": "linear-gradient(135deg,#2ECC71,#27AE60)",
      "icon": "fa-gamepad",
      "author": "CL",
      "authorAvatar": "恋",
      "views": "0",
      "comments": 7,
      "date": "2026年5年25日"
    }
  ],
  "tags": [
    "汉化",
    "SLG",
    "动态",
    "日式",
    "RPG",
    "更新",
    "中文",
    "PC+安卓",
    "欧美",
    "新作",
    "存档",
    "步兵",
    "巨乳",
    "爆乳",
    "互动",
    "亚洲",
    "安卓",
    "NTR",
    "探索",
    "ADV",
    "沙盒",
    "3D",
    "作弊",
    "ACT",
    "后宫",
    "像素"
  ],
  "comments": [
    {
      "author": "Dawn",
      "avatar": "D",
      "content": "感谢分享，游戏很好玩！"
    },
    {
      "author": "夜色",
      "avatar": "夜",
      "content": "请问解压密码是什么？"
    },
    {
      "author": "风之痕",
      "avatar": "风",
      "content": "期待更多汉化作品！"
    },
    {
      "author": "Moon",
      "avatar": "M",
      "content": "支持安卓版太赞了"
    }
  ],
  "randomPosts": [
    {
      "title": "大更新[沙盒SLG/家园后宫/全动态] 幸福岛幻想 V1.2.0.0 官中步兵版+DLC+存档 [8.30G]",
      "link": "/article.html?id=3",
      "gradient": "linear-gradient(135deg,#2ECC71,#27AE60)",
      "date": "2026年5年25日"
    },
    {
      "title": "更新[亚洲风SLG/堕母/动态] 妈妈为何这样 他让她堕落 He Maid Her Fall v0.8.6  官中步兵版+自带全回想 [PC+安卓8.60G]",
      "link": "/article.html?id=4",
      "gradient": "linear-gradient(135deg,#3498DB,#2980B9)",
      "date": "2026年5年25日"
    },
    {
      "title": "更新[国风仙侠RPG/像素动态] 合欢宗女修传 Ver0.25 官方中文版 [640M]",
      "link": "/article.html?id=5",
      "gradient": "linear-gradient(135deg,#2ECC71,#27AE60)",
      "date": "2026年5年25日"
    }
  ],
  "pagination": {
    "current": 1,
    "total": 113,
    "prevDisabled": true
  }
}